ca_certificates/__init__.py
hip_python_as_cuda-0.0.0.dist-info/METADATA
hip_python_as_cuda-0.0.0.dist-info/WHEEL
hip_python_as_cuda-0.0.0.dist-info/top_level.txt
hip_python_as_cuda-0.0.0.dist-info/RECORD
