Metadata-Version: 2.4
Name: hip-python-as-cuda
Version: 0.0.0
Summary: Dummy hip-python-as-cuda package for PyPI
Author-email: Your Name <you@example.com>
Requires-Python: >=3.7
